{
  "test_link": {
    "link": "https://colab.research.google.com/drive/1sAgmDFLseyL4HD0Aqvwf_wWE9YqkP9Iz?usp=sharing"
  },
  "test_read_data": {
    "lengths": [
      1750,
      250,
      500
    ]
  },
  "test_vocab": {
    "length": 7163,
    "tag2id_length": 7,
    "Spongebob": 1
  },
  "test_count_oov": {
    "dev_oov": 638,
    "test_oov": 1368
  },
  "test_prepare_data_loader": {
    "lengths": [
      110,
      16,
      32
    ]
  },
  "test_NERNet": {
    "f1": 0.9015164929673762,
    "f1_wo_o": 0.7558352989710782
  },
  "test_glove": {
    "f1": 0.902396100045163,
    "f1_wo_o": 0.8046047399658457
  }
}